{
  "삼성전자": "005930.KS",
  "SK하이닉스": "000660.KS",
  "SK텔레콤": "017670.KS",
  "두산에너빌리티": "034020.KS",
  "네이버": "035420.KS",
  "카카오": "035720.KS",
  "현대차": "005380.KS",
  "기아": "000270.KS",
  "LG전자": "066570.KS",
  "LG화학": "051910.KS",
  "POSCO홀딩스": "005490.KS",
  "KB금융": "105560.KS",
  "신한지주": "055550.KS",
  "하나금융지주": "086790.KS",
  "삼성바이오로직스": "207940.KS",
  "삼성SDI": "006400.KS",
  "현대모비스": "012330.KS",
  "LG에너지솔루션": "373220.KS",
  "셀트리온": "068270.KS",
  "SK이노베이션": "096770.KS",
  "NAVER": "035420.KS",
  "Kakao": "035720.KS",
  "삼성물산": "028260.KS",
  "한국전력": "015760.KS",
  "KT": "030200.KS",
  "LG생활건강": "051900.KS",
  "아모레퍼시픽": "090430.KS",
  "현대건설": "000720.KS",
  "삼성생명": "032830.KS",
  "SK": "034730.KS",
  "한화솔루션": "009830.KS",
  "HD현대": "267250.KS",
  "SK스퀘어": "402340.KS",
  "삼성엔지니어링": "028050.KS",
  "기업은행": "024110.KS",
  "SK케미칼": "285130.KS",
  "삼성전기": "009150.KS",
  "LG유플러스": "032640.KS",
  "대한항공": "003490.KS",
  "한국가스공사": "036460.KS",
  "SK바이오팜": "326030.KS",
  "삼성화재": "000810.KS",
  "현대제철": "004020.KS",
  "포스코퓨처엠": "003670.KS",
  "에코프로비엠": "247540.KS",
  "HMM": "011200.KS",
  "HD현대중공업": "329180.KS",
  "강원랜드": "035250.KS",
  "오리온": "271560.KS"
}
